filecontroller.py
filecontroller-1.1.dist-info/LICENSE.txt
filecontroller-1.1.dist-info/METADATA
filecontroller-1.1.dist-info/WHEEL
filecontroller-1.1.dist-info/top_level.txt
filecontroller-1.1.dist-info/RECORD
