Metadata-Version: 2.1
Name: filecontroller
Version: 1.1
Summary: FileController - The best user-friendly file manager
Home-page: UNKNOWN
Author: Alex M.
License: MIT
Project-URL: Source Code, https://github.com/alex-mst/filecontroller_public
Project-URL: Documentation, https://alex-mst.github.io/filecontroller/
Project-URL: Contact, https://discord.gg/HvdN9P85PP
Platform: UNKNOWN
Classifier: License :: OSI Approved :: MIT License
Classifier: Programming Language :: Python :: 3
Classifier: Programming Language :: Python :: 3.9
